README.md
pyproject.toml
shellhistory/__init__.py
shellhistory/__main__.py
shellhistory/app.py
shellhistory/cli.py
shellhistory/db.py
shellhistory/shellhistory.sh
shellhistory/static/css/home.css
shellhistory/static/js/codes.js
shellhistory/static/js/daily.js
shellhistory/static/js/daily_average.js
shellhistory/static/js/duration.js
shellhistory/static/js/home.js
shellhistory/static/js/hourly.js
shellhistory/static/js/hourly_average.js
shellhistory/static/js/length.js
shellhistory/static/js/markov.js
shellhistory/static/js/markov_full.js
shellhistory/static/js/monthly.js
shellhistory/static/js/monthly_average.js
shellhistory/static/js/over_time.js
shellhistory/static/js/top_commands.js
shellhistory/static/js/top_commands_full.js
shellhistory/static/js/trending.js
shellhistory/static/js/type.js
shellhistory/static/js/wordcloud.js
shellhistory/static/js/yearly.js
shellhistory/templates/admin/history_list.html
shellhistory/templates/admin/index.html
shellhistory/templates/codes.html
shellhistory/templates/daily.html
shellhistory/templates/daily_average.html
shellhistory/templates/duration.html
shellhistory/templates/home.html
shellhistory/templates/hourly.html
shellhistory/templates/hourly_average.html
shellhistory/templates/length.html
shellhistory/templates/markov.html
shellhistory/templates/markov_full.html
shellhistory/templates/monthly.html
shellhistory/templates/monthly_average.html
shellhistory/templates/over_time.html
shellhistory/templates/top_commands.html
shellhistory/templates/top_commands_full.html
shellhistory/templates/trending.html
shellhistory/templates/type.html
shellhistory/templates/yearly.html
shellhistory-0.2.4.dist-info/entry_points.txt
shellhistory-0.2.4.dist-info/LICENSE
shellhistory-0.2.4.dist-info/WHEEL
shellhistory-0.2.4.dist-info/METADATA
shellhistory-0.2.4.dist-info/RECORD
