Metadata-Version: 2.1
Name: shellhistory
Version: 0.2.4
Summary:  Visualize your shell usage with Highcharts!
Home-page: https://github.com/pawamoy/shell-history
License: ISC
Keywords: shell,bash,zsh,history,analysis,visualization
Author: Timothée Mazzucotelli
Author-email: pawamoy@pm.me
Requires-Python: >=3.6,<4.0
Classifier: License :: OSI Approved
Classifier: Programming Language :: Python :: 3
Classifier: Programming Language :: Python :: 3.6
Classifier: Programming Language :: Python :: 3.7
Requires-Dist: Flask-Admin (>=1.5,<2.0)
Requires-Dist: flask (>=1.0,<2.0)
Requires-Dist: sqlalchemy (>=1.3,<2.0)
Requires-Dist: tqdm (>=4.28,<5.0)
Project-URL: Repository, https://github.com/pawamoy/shell-history
